markdown_toc_segments/__init__.py
markdown_toc_segments/clean.py
markdown_toc_segments/footnote.py
markdown_toc_segments/main.py
markdown_toc_segments/segment.py
markdown_toc_segments/utils.py
markdown_toc_segments-0.0.4.dist-info/METADATA
markdown_toc_segments-0.0.4.dist-info/WHEEL
markdown_toc_segments-0.0.4.dist-info/RECORD
