Metadata-Version: 2.1
Name: markdown-toc-segments
Version: 0.0.4
Summary: Create markdown segments based on a table of contents
Home-page: https://mv3.dev
Author: Marcelino G. Veloso III
Author-email: mars@veloso.one
Requires-Python: >=3.11,<4.0
Classifier: Development Status :: 4 - Beta
Classifier: Framework :: Pytest
Classifier: Programming Language :: Python :: 3
Classifier: Programming Language :: Python :: 3.11
Classifier: Typing :: Typed
Requires-Dist: beautifulsoup4 (>=4.12.2,<5.0.0)
Requires-Dist: markdown (>=3.2,<4.0)
Requires-Dist: markdownify (>=0.11.6,<0.12.0)
Project-URL: Repository, https://github.com/justmars/markdown-toc-segments
